pwnchain/__init__.py
pwnchain/__main__.py
pwnchain/config.py
pwnchain/module.py
pwnchain/pwnchain_cli.py
pwnchain-0.2.0.dist-info/LICENSE
pwnchain-0.2.0.dist-info/METADATA
pwnchain-0.2.0.dist-info/WHEEL
pwnchain-0.2.0.dist-info/entry_points.txt
pwnchain-0.2.0.dist-info/top_level.txt
pwnchain-0.2.0.dist-info/RECORD
