Metadata-Version: 2.1
Name: pwnchain
Version: 0.2.0
Summary: Cascading different tools in automated fashion.
Home-page: https://github.com/nikolas-beisemann/pwnchain
Author: Nikolas Beisemann
Author-email: nikolas@disroot.org
License: UNKNOWN
Project-URL: Bug Tracker, https://github.com/nikolas-beisemann/pwnchain/issues
Platform: UNKNOWN
Classifier: Programming Language :: Python :: 3
Classifier: License :: OSI Approved :: GNU General Public License (GPL)
Classifier: Operating System :: OS Independent
Requires-Python: >=3.8
